.gitignore
LICENSE
README.rst
jinja2_hamlpy.py
setup.py
jinja2_hamlpy.egg-info/PKG-INFO
jinja2_hamlpy.egg-info/SOURCES.txt
jinja2_hamlpy.egg-info/dependency_links.txt
jinja2_hamlpy.egg-info/not-zip-safe
jinja2_hamlpy.egg-info/requires.txt
jinja2_hamlpy.egg-info/top_level.txt