Metadata-Version: 1.1
Name: jinja2-hamlpy
Version: 0.1
Summary: HamlPy extension for Jinja2
Home-page: http://github.com/grigi/jinja2-hamlpy
Author: Nickolas Grigoriadis
Author-email: nagrigoriadis@gmail.com
License: BSD
Keywords: jinja jinja2 templates haml hamlpy
Platform: any
Classifier: Environment :: Web Environment
Classifier: Intended Audience :: Developers
Classifier: Intended Audience :: System Administrators
Classifier: Operating System :: OS Independent
Classifier: License :: OSI Approved :: BSD License
Classifier: Programming Language :: Python
Classifier: Topic :: Internet :: WWW/HTTP :: Dynamic Content
Classifier: Topic :: Software Development :: Libraries :: Python Modules
Classifier: Topic :: Text Processing :: Markup :: HTML
